ebcic/__init__.py
ebcic/__main__.py
ebcic/ebcic.py
ebcic-0.0.4.dist-info/LICENSE
ebcic-0.0.4.dist-info/METADATA
ebcic-0.0.4.dist-info/WHEEL
ebcic-0.0.4.dist-info/top_level.txt
ebcic-0.0.4.dist-info/RECORD
