Metadata-Version: 2.1
Name: ebcic
Version: 0.0.4
Summary: EBCIC (Exact Binomial Confidence Interval Calculator) package
Home-page: https://github.com/KazKobara/ebcic
Author: Kaz KOBARA
Author-email: M-kaz-ml@aist.go.jp
License: UNKNOWN
Keywords: statistics,binomial,confidence interval
Platform: UNKNOWN
Classifier: Development Status :: 5 - Production/Stable
Classifier: Programming Language :: Python :: 3
Classifier: Operating System :: OS Independent
Requires-Python: >=3.8
Requires-Dist: scipy (>=1.7)
Requires-Dist: matplotlib
